certstore/__init__.py
certstore/certstore.py
certstore-0.0.2.dist-info/DESCRIPTION.rst
certstore-0.0.2.dist-info/METADATA
certstore-0.0.2.dist-info/RECORD
certstore-0.0.2.dist-info/WHEEL
certstore-0.0.2.dist-info/metadata.json
certstore-0.0.2.dist-info/pbr.json
certstore-0.0.2.dist-info/top_level.txt
