Metadata-Version: 2.0
Name: certstore
Version: 0.0.2
Summary: Platform independent access to system certificate store
Home-page: https://certstore.readthedocs.io/
Author: Jon Everett
Author-email: jon.everett@protonmail.com
License: Apache-2
Keywords: cert
Requires-Dist: wincertstore; (os_name == 'nt')
